[
  {
    "src": "https://i.ibb.co/28PpJtZ/IMG-20221028-191101.jpg",
    "name": "p1"
  },
  {
    "src": "https://i.ibb.co/BGkYNZz/IMG-20240806-200303.jpg",
    "name": "p2"
  },
  {
    "src": "https://i.ibb.co/2gtntL5/IMG-20240806-200319.jpg",
    "name": "p3"
  },
  {
    "src": "https://i.ibb.co/dQDM1qJ/Snapchat-158197462.jpg",
    "name": "p4"
  },
  {
    "src": "https://i.ibb.co/8X73xR0/Snapchat-631997259.jpg",
    "name": "p5"
  },
  {
    "src": "https://i.ibb.co/NxNkf1J/Snapchat-896313053.jpg",
    "name": "p6"
  }
]
